setuptools_compile_po/__init__.py
setuptools_compile_po-1.0.0.dist-info/licenses/LICENSE
setuptools_compile_po-1.0.0.dist-info/METADATA
setuptools_compile_po-1.0.0.dist-info/WHEEL
setuptools_compile_po-1.0.0.dist-info/entry_points.txt
setuptools_compile_po-1.0.0.dist-info/top_level.txt
setuptools_compile_po-1.0.0.dist-info/RECORD
