Metadata-Version: 2.4
Name: setuptools-compile-po
Version: 1.0.0
Summary: Compile po files to mo files.
Author-email: Zdeněk Böhm <zdenek.bohm@nic.cz>
License-Expression: MIT
Project-URL: Homepage, https://github.com/zbohm/setuptools-compile-po
Project-URL: Repository, https://github.com/zbohm/setuptools-compile-po
Classifier: Development Status :: 5 - Production/Stable
Classifier: Intended Audience :: Developers
Classifier: Programming Language :: Python :: 3
Classifier: Programming Language :: Python :: 3 :: Only
Classifier: Topic :: Software Development :: Libraries :: Python Modules
Classifier: Topic :: System :: Archiving :: Packaging
Classifier: Topic :: System :: Systems Administration
Classifier: Topic :: Utilities
Requires-Python: >=3.9
License-File: LICENSE
Requires-Dist: setuptools
Dynamic: license-file
